[
    {
        "model": "hitcount.hitcount",
        "pk": 1,
        "fields": {
            "hits": 947,
            "modified": "2023-09-16T18:39:05.914Z",
            "content_type": 9,
            "object_pk": 1
        }
    },
    {
        "model": "hitcount.hitcount",
        "pk": 2,
        "fields": {
            "hits": 297,
            "modified": "2023-09-16T18:39:05.914Z",
            "content_type": 9,
            "object_pk": 2
        }
    },
    {
        "model": "hitcount.hitcount",
        "pk": 3,
        "fields": {
            "hits": 897,
            "modified": "2023-09-16T18:39:05.914Z",
            "content_type": 9,
            "object_pk": 3
        }
    },
    {
        "model": "hitcount.hitcount",
        "pk": 4,
        "fields": {
            "hits": 501,
            "modified": "2023-09-16T18:39:05.914Z",
            "content_type": 9,
            "object_pk": 4
        }
    },
    {
        "model": "hitcount.hitcount",
        "pk": 5,
        "fields": {
            "hits": 243,
            "modified": "2023-09-16T18:39:05.914Z",
            "content_type": 9,
            "object_pk": 5
        }
    },
    {
        "model": "hitcount.hitcount",
        "pk": 6,
        "fields": {
            "hits": 137,
            "modified": "2023-09-16T18:39:05.914Z",
            "content_type": 9,
            "object_pk": 6
        }
    },
    {
        "model": "hitcount.hitcount",
        "pk": 7,
        "fields": {
            "hits": 905,
            "modified": "2023-09-16T18:39:05.914Z",
            "content_type": 9,
            "object_pk": 7
        }
    },
    {
        "model": "hitcount.hitcount",
        "pk": 8,
        "fields": {
            "hits": 395,
            "modified": "2023-09-16T18:39:05.914Z",
            "content_type": 9,
            "object_pk": 8
        }
    },
    {
        "model": "hitcount.hitcount",
        "pk": 9,
        "fields": {
            "hits": 547,
            "modified": "2023-09-16T18:39:05.914Z",
            "content_type": 9,
            "object_pk": 9
        }
    },
    {
        "model": "hitcount.hitcount",
        "pk": 10,
        "fields": {
            "hits": 944,
            "modified": "2023-09-16T18:39:05.914Z",
            "content_type": 9,
            "object_pk": 10
        }
    },
    {
        "model": "hitcount.hitcount",
        "pk": 11,
        "fields": {
            "hits": 125,
            "modified": "2023-09-16T18:39:05.914Z",
            "content_type": 9,
            "object_pk": 11
        }
    },
    {
        "model": "hitcount.hitcount",
        "pk": 12,
        "fields": {
            "hits": 163,
            "modified": "2023-09-16T18:39:05.914Z",
            "content_type": 9,
            "object_pk": 12
        }
    },
    {
        "model": "hitcount.hitcount",
        "pk": 13,
        "fields": {
            "hits": 649,
            "modified": "2023-09-16T18:39:05.914Z",
            "content_type": 9,
            "object_pk": 13
        }
    },
    {
        "model": "hitcount.hitcount",
        "pk": 14,
        "fields": {
            "hits": 784,
            "modified": "2023-09-16T18:39:05.914Z",
            "content_type": 9,
            "object_pk": 14
        }
    },
    {
        "model": "hitcount.hitcount",
        "pk": 15,
        "fields": {
            "hits": 828,
            "modified": "2023-09-16T18:39:05.914Z",
            "content_type": 9,
            "object_pk": 15
        }
    },
    {
        "model": "hitcount.hitcount",
        "pk": 16,
        "fields": {
            "hits": 800,
            "modified": "2023-09-16T18:39:05.914Z",
            "content_type": 9,
            "object_pk": 16
        }
    },
    {
        "model": "hitcount.hitcount",
        "pk": 17,
        "fields": {
            "hits": 877,
            "modified": "2023-09-16T18:39:05.914Z",
            "content_type": 9,
            "object_pk": 17
        }
    },
    {
        "model": "hitcount.hitcount",
        "pk": 18,
        "fields": {
            "hits": 275,
            "modified": "2023-09-16T18:39:05.914Z",
            "content_type": 9,
            "object_pk": 18
        }
    },
    {
        "model": "hitcount.hitcount",
        "pk": 19,
        "fields": {
            "hits": 455,
            "modified": "2023-09-16T18:39:05.914Z",
            "content_type": 9,
            "object_pk": 19
        }
    },
    {
        "model": "hitcount.hitcount",
        "pk": 20,
        "fields": {
            "hits": 193,
            "modified": "2023-09-16T18:39:05.914Z",
            "content_type": 9,
            "object_pk": 20
        }
    },
    {
        "model": "hitcount.hitcount",
        "pk": 21,
        "fields": {
            "hits": 891,
            "modified": "2023-09-16T18:39:05.914Z",
            "content_type": 9,
            "object_pk": 21
        }
    },
    {
        "model": "hitcount.hitcount",
        "pk": 22,
        "fields": {
            "hits": 131,
            "modified": "2023-09-16T18:39:05.914Z",
            "content_type": 9,
            "object_pk": 22
        }
    },
    {
        "model": "hitcount.hitcount",
        "pk": 23,
        "fields": {
            "hits": 107,
            "modified": "2023-09-16T18:39:05.914Z",
            "content_type": 9,
            "object_pk": 23
        }
    },
    {
        "model": "hitcount.hitcount",
        "pk": 24,
        "fields": {
            "hits": 846,
            "modified": "2023-09-16T18:39:05.914Z",
            "content_type": 9,
            "object_pk": 24
        }
    },
    {
        "model": "hitcount.hitcount",
        "pk": 25,
        "fields": {
            "hits": 774,
            "modified": "2023-09-16T18:39:05.914Z",
            "content_type": 9,
            "object_pk": 25
        }
    },
    {
        "model": "hitcount.hitcount",
        "pk": 26,
        "fields": {
            "hits": 910,
            "modified": "2023-09-16T18:39:05.914Z",
            "content_type": 9,
            "object_pk": 26
        }
    },
    {
        "model": "hitcount.hitcount",
        "pk": 27,
        "fields": {
            "hits": 417,
            "modified": "2023-09-16T18:39:05.914Z",
            "content_type": 9,
            "object_pk": 27
        }
    },
    {
        "model": "hitcount.hitcount",
        "pk": 28,
        "fields": {
            "hits": 820,
            "modified": "2023-09-16T18:39:05.914Z",
            "content_type": 9,
            "object_pk": 28
        }
    },
    {
        "model": "hitcount.hitcount",
        "pk": 29,
        "fields": {
            "hits": 639,
            "modified": "2023-09-16T18:39:05.914Z",
            "content_type": 9,
            "object_pk": 29
        }
    },
    {
        "model": "hitcount.hitcount",
        "pk": 30,
        "fields": {
            "hits": 727,
            "modified": "2023-09-16T18:39:05.914Z",
            "content_type": 9,
            "object_pk": 30
        }
    },
    {
        "model": "hitcount.hitcount",
        "pk": 31,
        "fields": {
            "hits": 720,
            "modified": "2023-09-16T18:39:05.914Z",
            "content_type": 9,
            "object_pk": 31
        }
    },
    {
        "model": "hitcount.hitcount",
        "pk": 32,
        "fields": {
            "hits": 459,
            "modified": "2023-09-16T18:39:05.914Z",
            "content_type": 9,
            "object_pk": 32
        }
    },
    {
        "model": "hitcount.hitcount",
        "pk": 33,
        "fields": {
            "hits": 190,
            "modified": "2023-09-16T18:39:05.914Z",
            "content_type": 9,
            "object_pk": 33
        }
    },
    {
        "model": "hitcount.hitcount",
        "pk": 34,
        "fields": {
            "hits": 254,
            "modified": "2023-09-16T18:39:05.914Z",
            "content_type": 9,
            "object_pk": 34
        }
    },
    {
        "model": "hitcount.hitcount",
        "pk": 35,
        "fields": {
            "hits": 651,
            "modified": "2023-09-16T18:39:05.914Z",
            "content_type": 9,
            "object_pk": 35
        }
    },
    {
        "model": "hitcount.hitcount",
        "pk": 36,
        "fields": {
            "hits": 189,
            "modified": "2023-09-16T18:39:05.914Z",
            "content_type": 9,
            "object_pk": 36
        }
    },
    {
        "model": "hitcount.hitcount",
        "pk": 37,
        "fields": {
            "hits": 468,
            "modified": "2023-09-16T18:39:05.914Z",
            "content_type": 9,
            "object_pk": 37
        }
    },
    {
        "model": "hitcount.hitcount",
        "pk": 38,
        "fields": {
            "hits": 310,
            "modified": "2023-09-16T18:39:05.914Z",
            "content_type": 9,
            "object_pk": 38
        }
    },
    {
        "model": "hitcount.hitcount",
        "pk": 39,
        "fields": {
            "hits": 424,
            "modified": "2023-09-16T18:39:05.914Z",
            "content_type": 9,
            "object_pk": 39
        }
    },
    {
        "model": "hitcount.hitcount",
        "pk": 40,
        "fields": {
            "hits": 106,
            "modified": "2023-09-16T18:39:05.914Z",
            "content_type": 9,
            "object_pk": 40
        }
    },
    {
        "model": "hitcount.hitcount",
        "pk": 41,
        "fields": {
            "hits": 820,
            "modified": "2023-09-16T18:39:05.914Z",
            "content_type": 9,
            "object_pk": 41
        }
    },
    {
        "model": "hitcount.hitcount",
        "pk": 42,
        "fields": {
            "hits": 570,
            "modified": "2023-09-16T18:39:05.914Z",
            "content_type": 9,
            "object_pk": 42
        }
    },
    {
        "model": "hitcount.hitcount",
        "pk": 43,
        "fields": {
            "hits": 400,
            "modified": "2023-09-16T18:39:05.914Z",
            "content_type": 9,
            "object_pk": 43
        }
    },
    {
        "model": "hitcount.hitcount",
        "pk": 44,
        "fields": {
            "hits": 327,
            "modified": "2023-09-16T18:39:05.914Z",
            "content_type": 9,
            "object_pk": 44
        }
    },
    {
        "model": "hitcount.hitcount",
        "pk": 45,
        "fields": {
            "hits": 644,
            "modified": "2023-09-16T18:39:05.914Z",
            "content_type": 9,
            "object_pk": 45
        }
    },
    {
        "model": "hitcount.hitcount",
        "pk": 46,
        "fields": {
            "hits": 693,
            "modified": "2023-09-16T18:39:05.914Z",
            "content_type": 9,
            "object_pk": 46
        }
    },
    {
        "model": "hitcount.hitcount",
        "pk": 47,
        "fields": {
            "hits": 90,
            "modified": "2023-09-16T18:39:05.914Z",
            "content_type": 9,
            "object_pk": 47
        }
    },
    {
        "model": "hitcount.hitcount",
        "pk": 48,
        "fields": {
            "hits": 525,
            "modified": "2023-09-16T18:39:05.914Z",
            "content_type": 9,
            "object_pk": 48
        }
    },
    {
        "model": "hitcount.hitcount",
        "pk": 49,
        "fields": {
            "hits": 433,
            "modified": "2023-09-16T18:39:05.914Z",
            "content_type": 9,
            "object_pk": 49
        }
    },
    {
        "model": "hitcount.hitcount",
        "pk": 50,
        "fields": {
            "hits": 780,
            "modified": "2023-09-16T18:39:05.914Z",
            "content_type": 9,
            "object_pk": 50
        }
    },
    {
        "model": "hitcount.hitcount",
        "pk": 51,
        "fields": {
            "hits": 122,
            "modified": "2023-09-16T18:39:05.914Z",
            "content_type": 9,
            "object_pk": 51
        }
    },
    {
        "model": "hitcount.hitcount",
        "pk": 52,
        "fields": {
            "hits": 281,
            "modified": "2023-09-16T18:39:05.914Z",
            "content_type": 9,
            "object_pk": 52
        }
    },
    {
        "model": "hitcount.hitcount",
        "pk": 53,
        "fields": {
            "hits": 878,
            "modified": "2023-09-16T18:39:05.914Z",
            "content_type": 9,
            "object_pk": 53
        }
    },
    {
        "model": "hitcount.hitcount",
        "pk": 54,
        "fields": {
            "hits": 855,
            "modified": "2023-09-16T18:39:05.914Z",
            "content_type": 9,
            "object_pk": 54
        }
    },
    {
        "model": "hitcount.hitcount",
        "pk": 55,
        "fields": {
            "hits": 486,
            "modified": "2023-09-16T18:39:05.914Z",
            "content_type": 9,
            "object_pk": 55
        }
    },
    {
        "model": "hitcount.hitcount",
        "pk": 56,
        "fields": {
            "hits": 341,
            "modified": "2023-09-16T18:39:05.914Z",
            "content_type": 9,
            "object_pk": 56
        }
    },
    {
        "model": "hitcount.hitcount",
        "pk": 57,
        "fields": {
            "hits": 922,
            "modified": "2023-09-16T18:39:05.914Z",
            "content_type": 9,
            "object_pk": 57
        }
    },
    {
        "model": "hitcount.hitcount",
        "pk": 58,
        "fields": {
            "hits": 738,
            "modified": "2023-09-16T18:39:05.914Z",
            "content_type": 9,
            "object_pk": 58
        }
    },
    {
        "model": "hitcount.hitcount",
        "pk": 59,
        "fields": {
            "hits": 458,
            "modified": "2023-09-16T18:39:05.914Z",
            "content_type": 9,
            "object_pk": 59
        }
    },
    {
        "model": "hitcount.hitcount",
        "pk": 60,
        "fields": {
            "hits": 602,
            "modified": "2023-09-16T18:39:05.914Z",
            "content_type": 9,
            "object_pk": 60
        }
    },
    {
        "model": "hitcount.hitcount",
        "pk": 61,
        "fields": {
            "hits": 525,
            "modified": "2023-09-16T18:39:05.914Z",
            "content_type": 9,
            "object_pk": 61
        }
    },
    {
        "model": "hitcount.hitcount",
        "pk": 62,
        "fields": {
            "hits": 493,
            "modified": "2023-09-16T18:39:05.914Z",
            "content_type": 9,
            "object_pk": 62
        }
    },
    {
        "model": "hitcount.hitcount",
        "pk": 63,
        "fields": {
            "hits": 168,
            "modified": "2023-09-16T18:39:05.914Z",
            "content_type": 9,
            "object_pk": 63
        }
    },
    {
        "model": "hitcount.hitcount",
        "pk": 64,
        "fields": {
            "hits": 341,
            "modified": "2023-09-16T18:39:05.914Z",
            "content_type": 9,
            "object_pk": 64
        }
    },
    {
        "model": "hitcount.hitcount",
        "pk": 65,
        "fields": {
            "hits": 970,
            "modified": "2023-09-16T18:39:05.914Z",
            "content_type": 9,
            "object_pk": 65
        }
    },
    {
        "model": "hitcount.hitcount",
        "pk": 66,
        "fields": {
            "hits": 74,
            "modified": "2023-09-16T18:39:05.914Z",
            "content_type": 9,
            "object_pk": 66
        }
    },
    {
        "model": "hitcount.hitcount",
        "pk": 67,
        "fields": {
            "hits": 369,
            "modified": "2023-09-16T18:39:05.914Z",
            "content_type": 9,
            "object_pk": 67
        }
    },
    {
        "model": "hitcount.hitcount",
        "pk": 68,
        "fields": {
            "hits": 205,
            "modified": "2023-09-16T18:39:05.914Z",
            "content_type": 9,
            "object_pk": 68
        }
    },
    {
        "model": "hitcount.hitcount",
        "pk": 69,
        "fields": {
            "hits": 650,
            "modified": "2023-09-16T18:39:05.914Z",
            "content_type": 9,
            "object_pk": 69
        }
    },
    {
        "model": "hitcount.hitcount",
        "pk": 70,
        "fields": {
            "hits": 710,
            "modified": "2023-09-16T18:39:05.914Z",
            "content_type": 9,
            "object_pk": 70
        }
    },
    {
        "model": "hitcount.hitcount",
        "pk": 71,
        "fields": {
            "hits": 824,
            "modified": "2023-09-16T18:39:05.914Z",
            "content_type": 9,
            "object_pk": 71
        }
    },
    {
        "model": "hitcount.hitcount",
        "pk": 72,
        "fields": {
            "hits": 282,
            "modified": "2023-09-16T18:39:05.914Z",
            "content_type": 9,
            "object_pk": 72
        }
    },
    {
        "model": "hitcount.hitcount",
        "pk": 73,
        "fields": {
            "hits": 559,
            "modified": "2023-09-16T18:39:05.914Z",
            "content_type": 9,
            "object_pk": 73
        }
    },
    {
        "model": "hitcount.hitcount",
        "pk": 74,
        "fields": {
            "hits": 825,
            "modified": "2023-09-16T18:39:05.914Z",
            "content_type": 9,
            "object_pk": 74
        }
    },
    {
        "model": "hitcount.hitcount",
        "pk": 75,
        "fields": {
            "hits": 843,
            "modified": "2023-09-16T18:39:05.914Z",
            "content_type": 9,
            "object_pk": 75
        }
    },
    {
        "model": "hitcount.hitcount",
        "pk": 76,
        "fields": {
            "hits": 219,
            "modified": "2023-09-16T18:39:05.914Z",
            "content_type": 9,
            "object_pk": 76
        }
    },
    {
        "model": "hitcount.hitcount",
        "pk": 77,
        "fields": {
            "hits": 319,
            "modified": "2023-09-16T18:39:05.914Z",
            "content_type": 9,
            "object_pk": 77
        }
    },
    {
        "model": "hitcount.hitcount",
        "pk": 78,
        "fields": {
            "hits": 463,
            "modified": "2023-09-16T18:39:05.914Z",
            "content_type": 9,
            "object_pk": 78
        }
    },
    {
        "model": "hitcount.hitcount",
        "pk": 79,
        "fields": {
            "hits": 377,
            "modified": "2023-09-16T18:39:05.914Z",
            "content_type": 9,
            "object_pk": 79
        }
    },
    {
        "model": "hitcount.hitcount",
        "pk": 80,
        "fields": {
            "hits": 763,
            "modified": "2023-09-16T18:39:05.914Z",
            "content_type": 9,
            "object_pk": 80
        }
    },
    {
        "model": "hitcount.hitcount",
        "pk": 81,
        "fields": {
            "hits": 886,
            "modified": "2023-09-16T18:39:05.914Z",
            "content_type": 9,
            "object_pk": 81
        }
    },
    {
        "model": "hitcount.hitcount",
        "pk": 82,
        "fields": {
            "hits": 814,
            "modified": "2023-09-16T18:39:05.914Z",
            "content_type": 9,
            "object_pk": 82
        }
    },
    {
        "model": "hitcount.hitcount",
        "pk": 83,
        "fields": {
            "hits": 569,
            "modified": "2023-09-16T18:39:05.914Z",
            "content_type": 9,
            "object_pk": 83
        }
    },
    {
        "model": "hitcount.hitcount",
        "pk": 84,
        "fields": {
            "hits": 821,
            "modified": "2023-09-16T18:39:05.914Z",
            "content_type": 9,
            "object_pk": 84
        }
    },
    {
        "model": "hitcount.hitcount",
        "pk": 85,
        "fields": {
            "hits": 953,
            "modified": "2023-09-16T18:39:05.914Z",
            "content_type": 9,
            "object_pk": 85
        }
    },
    {
        "model": "hitcount.hitcount",
        "pk": 86,
        "fields": {
            "hits": 853,
            "modified": "2023-09-16T18:39:05.914Z",
            "content_type": 9,
            "object_pk": 86
        }
    },
    {
        "model": "hitcount.hitcount",
        "pk": 87,
        "fields": {
            "hits": 557,
            "modified": "2023-09-16T18:39:05.914Z",
            "content_type": 9,
            "object_pk": 87
        }
    },
    {
        "model": "hitcount.hitcount",
        "pk": 88,
        "fields": {
            "hits": 386,
            "modified": "2023-09-16T18:39:05.914Z",
            "content_type": 9,
            "object_pk": 88
        }
    },
    {
        "model": "hitcount.hitcount",
        "pk": 89,
        "fields": {
            "hits": 227,
            "modified": "2023-09-16T18:39:05.914Z",
            "content_type": 9,
            "object_pk": 89
        }
    },
    {
        "model": "hitcount.hitcount",
        "pk": 90,
        "fields": {
            "hits": 559,
            "modified": "2023-09-16T18:39:05.914Z",
            "content_type": 9,
            "object_pk": 90
        }
    },
    {
        "model": "hitcount.hitcount",
        "pk": 91,
        "fields": {
            "hits": 981,
            "modified": "2023-09-16T18:39:05.914Z",
            "content_type": 9,
            "object_pk": 91
        }
    },
    {
        "model": "hitcount.hitcount",
        "pk": 92,
        "fields": {
            "hits": 210,
            "modified": "2023-09-16T18:39:05.914Z",
            "content_type": 9,
            "object_pk": 92
        }
    },
    {
        "model": "hitcount.hitcount",
        "pk": 93,
        "fields": {
            "hits": 578,
            "modified": "2023-09-16T18:39:05.914Z",
            "content_type": 9,
            "object_pk": 93
        }
    },
    {
        "model": "hitcount.hitcount",
        "pk": 94,
        "fields": {
            "hits": 243,
            "modified": "2023-09-16T18:39:05.914Z",
            "content_type": 9,
            "object_pk": 94
        }
    },
    {
        "model": "hitcount.hitcount",
        "pk": 95,
        "fields": {
            "hits": 589,
            "modified": "2023-09-16T18:39:05.914Z",
            "content_type": 9,
            "object_pk": 95
        }
    },
    {
        "model": "hitcount.hitcount",
        "pk": 96,
        "fields": {
            "hits": 570,
            "modified": "2023-09-16T18:39:05.914Z",
            "content_type": 9,
            "object_pk": 96
        }
    },
    {
        "model": "hitcount.hitcount",
        "pk": 97,
        "fields": {
            "hits": 599,
            "modified": "2023-09-16T18:39:05.914Z",
            "content_type": 9,
            "object_pk": 97
        }
    },
    {
        "model": "hitcount.hitcount",
        "pk": 98,
        "fields": {
            "hits": 595,
            "modified": "2023-09-16T18:39:05.914Z",
            "content_type": 9,
            "object_pk": 98
        }
    },
    {
        "model": "hitcount.hitcount",
        "pk": 99,
        "fields": {
            "hits": 325,
            "modified": "2023-09-16T18:39:05.914Z",
            "content_type": 9,
            "object_pk": 99
        }
    },
    {
        "model": "hitcount.hitcount",
        "pk": 100,
        "fields": {
            "hits": 272,
            "modified": "2023-09-16T18:39:05.914Z",
            "content_type": 9,
            "object_pk": 100
        }
    }
]